ucitests
