Metadata-Version: 1.0
Name: ucitests
Version: 0.4.1
Summary: Ubuntu Continuous Integration test tools.
Home-page: https://launchpad.net/uci-tests
Author: Vincent Ladeuil
Author-email: vila+qa@canonical.com
License: GPLv3
Platform: UNKNOWN
